unimemory/__init__.py
unimemory/client.py
unimemory/types.py
unimemory-1.0.2.dist-info/METADATA
unimemory-1.0.2.dist-info/WHEEL
unimemory-1.0.2.dist-info/top_level.txt
unimemory-1.0.2.dist-info/RECORD
