Metadata-Version: 2.4
Name: unimemory
Version: 1.0.2
Summary: UniMemory SDK - The memory layer for your AI apps.
Author-email: UniMemory <hello@unimemory.ai>
License-Expression: MIT
Project-URL: Homepage, https://unimemory.ai
Project-URL: Repository, https://github.com/shreyasgurav/UniMemory
Keywords: memory,ai,embeddings,search,vector,llm
Classifier: Development Status :: 4 - Beta
Classifier: Intended Audience :: Developers
Classifier: Programming Language :: Python :: 3
Classifier: Programming Language :: Python :: 3.8
Classifier: Programming Language :: Python :: 3.9
Classifier: Programming Language :: Python :: 3.10
Classifier: Programming Language :: Python :: 3.11
Classifier: Programming Language :: Python :: 3.12
Requires-Python: >=3.8
Requires-Dist: httpx>=0.25.0
Requires-Dist: pydantic>=2.0.0
